arque/__init__.py
arque-1.1.0.dist-info/LICENSE
arque-1.1.0.dist-info/METADATA
arque-1.1.0.dist-info/WHEEL
arque-1.1.0.dist-info/top_level.txt
arque-1.1.0.dist-info/RECORD
