Metadata-Version: 2.1
Name: arque
Version: 1.1.0
Summary: Asyncio Reliable Queue (based on redis)
Home-page: https://github.com/code-impactor/arque
Author: Andrei Roskach
Author-email: code.impactor@gmail.com
License: MIT
Download-URL: https://github.com/code-impactor/arque/releases/tag/1.1.0
Keywords: asyncio,redis,reliable,queue,asynchronous,python,reliable-queue,work-queue,delay,delayed,jobs,delayed-queue,repeated,tasks,dead letter,failed
Platform: Any
Classifier: Intended Audience :: Developers
Classifier: Programming Language :: Python :: 3.7
Classifier: Natural Language :: English
Classifier: License :: OSI Approved :: MIT License
Classifier: Operating System :: OS Independent
Classifier: Topic :: Database
Classifier: Topic :: Software Development :: Libraries
Requires-Python: >=3.7
Requires-Dist: aioredis (>=1.2.0)
